multimv/__init__.py
multimv/vendor/toposort/__init__.py
multimv-0.7.0.dist-info/entry_points.txt
multimv-0.7.0.dist-info/WHEEL
multimv-0.7.0.dist-info/METADATA
multimv-0.7.0.dist-info/RECORD
